api/__init__.py
api/api.py
api/cache.py
api/db.py
api/logger.py
api/main.py
api/message_broker.py
api/models.py
neojelll_url_shortener_api-0.1.27.dist-info/METADATA
neojelll_url_shortener_api-0.1.27.dist-info/WHEEL
neojelll_url_shortener_api-0.1.27.dist-info/entry_points.txt
neojelll_url_shortener_api-0.1.27.dist-info/RECORD
